{
    "journal": "JF",
    "volume": "38",
    "issue": "2",
    "date": "May 1983",
    "page": "Pages: i-vii, 283-661, viii-xx",
    "article": [
        {
            "no": "1",
            "title": "Front Matter",
            "date": "May 1983",
            "author": [],
            "abstract": "",
            "link": "https://doi.org/10.1111/j.1540-6261.1983.tb00915.x"
        },
        {
            "no": "2",
            "title": "Nonnegative or Not Nonnegative: A Question about CAPMs",
            "date": "May 1983",
            "author": [
                "HARRY M. MARKOWITZ"
            ],
            "abstract": "",
            "link": "https://doi.org/10.1111/j.1540-6261.1983.tb02234.x"
        },
        {
            "no": "3",
            "title": "Corporate Acquisitions: A Theory of Special Cases? A Review of Event Studies Applied to Acquisitions",
            "date": "May 1983",
            "author": [
                "J. FRED WESTON",
                "PAUL HALPERN"
            ],
            "abstract": "",
            "link": "https://doi.org/10.1111/j.1540-6261.1983.tb02235.x"
        },
        {
            "no": "4",
            "title": "The Cities Service Takeover: A Case Study",
            "date": "May 1983",
            "author": [
                "RICHARD S. RUBACK"
            ],
            "abstract": "",
            "link": "https://doi.org/10.1111/j.1540-6261.1983.tb02236.x"
        },
        {
            "no": "5",
            "title": "Tender Offers and Management Resistance",
            "date": "May 1983",
            "author": [
                "DAVID P. BARON"
            ],
            "abstract": "",
            "link": "https://doi.org/10.1111/j.1540-6261.1983.tb02237.x"
        },
        {
            "no": "6",
            "title": "DISCUSSION",
            "date": "May 1983",
            "author": [
                "J. FRED WESTON"
            ],
            "abstract": "",
            "link": "https://doi.org/10.1111/j.1540-6261.1983.tb02238.x"
        },
        {
            "no": "7",
            "title": "DISCUSSION",
            "date": "May 1983",
            "author": [
                "ROBERT S. HARRIS"
            ],
            "abstract": "",
            "link": "https://doi.org/10.1111/j.1540-6261.1983.tb02239.x"
        },
        {
            "no": "8",
            "title": "A Generalized Cash Flow Approach to Short\u2010Term Financial Decisions",
            "date": "May 1983",
            "author": [
                "GERALD A. POGUE",
                "WILLIAM L. SARTORIS",
                "NED C. HILL"
            ],
            "abstract": "",
            "link": "https://doi.org/10.1111/j.1540-6261.1983.tb02240.x"
        },
        {
            "no": "9",
            "title": "What Lockbox and Disbursement Models Really Do",
            "date": "May 1983",
            "author": [
                "STEVEN F. MAIER",
                "JAMES H. VANDER WEIDE"
            ],
            "abstract": "",
            "link": "https://doi.org/10.1111/j.1540-6261.1983.tb02241.x"
        },
        {
            "no": "10",
            "title": "The Design of a Company's Banking System",
            "date": "May 1983",
            "author": [
                "BERNELL K. STONE"
            ],
            "abstract": "",
            "link": "https://doi.org/10.1111/j.1540-6261.1983.tb02242.x"
        },
        {
            "no": "11",
            "title": "DISCUSSION",
            "date": "May 1983",
            "author": [
                "J. G. Kallberg"
            ],
            "abstract": "",
            "link": "https://doi.org/10.1111/j.1540-6261.1983.tb02243.x"
        },
        {
            "no": "12",
            "title": "DISCUSSION",
            "date": "May 1983",
            "author": [
                "GARY W. EMERY"
            ],
            "abstract": "",
            "link": "https://doi.org/10.1111/j.1540-6261.1983.tb02244.x"
        },
        {
            "no": "13",
            "title": "Asymmetry of Information, Regulatory Lags and Optimal Incentive Contracts: Theory and Evidence",
            "date": "May 1983",
            "author": [
                "RICHARD S. BOWER",
                "KOSE JOHN",
                "ANTHONY SAUNDERS"
            ],
            "abstract": "",
            "link": "https://doi.org/10.1111/j.1540-6261.1983.tb02245.x"
        },
        {
            "no": "14",
            "title": "Regulation, Regulatory Lag, and the Use of Futures Markets",
            "date": "May 1983",
            "author": [
                "ROBERT W. KOLB",
                "ROGER A. MORIN",
                "GERALD D. GAY"
            ],
            "abstract": "",
            "link": "https://doi.org/10.1111/j.1540-6261.1983.tb02246.x"
        },
        {
            "no": "15",
            "title": "INFLATION RISK AND REGULATORY LAG",
            "date": "May 1983",
            "author": [
                "WILLARD T. CARLETON",
                "DONALD R. CHAMBERS",
                "JOSEF LAKONISHOK"
            ],
            "abstract": "",
            "link": "https://doi.org/10.1111/j.1540-6261.1983.tb02247.x"
        },
        {
            "no": "16",
            "title": "DISCUSSION",
            "date": "May 1983",
            "author": [
                "GEORGE R. HALL"
            ],
            "abstract": "",
            "link": "https://doi.org/10.1111/j.1540-6261.1983.tb02248.x"
        },
        {
            "no": "17",
            "title": "Discussion",
            "date": "May 1983",
            "author": [
                "PAUL HALPERN"
            ],
            "abstract": "",
            "link": "https://doi.org/10.1111/j.1540-6261.1983.tb02249.x"
        },
        {
            "no": "18",
            "title": "EXTERNAL CURRENCY MARKET EQUILIBRIUM AND ITS IMPLICATIONS FOR REGULATION OF THE EUROCURRENCY MARKET\u2020\u2020",
            "date": "May 1983",
            "author": [
                "SANDRA SCHICKELE",
                "DENNIS E. LOGUE",
                "LEMMA W. SENBET"
            ],
            "abstract": "",
            "link": "https://doi.org/10.1111/j.1540-6261.1983.tb02250.x"
        },
        {
            "no": "19",
            "title": "International Arbitrage Pricing Theory",
            "date": "May 1983",
            "author": [
                "BRUNO SOLNIK"
            ],
            "abstract": "",
            "link": "https://doi.org/10.1111/j.1540-6261.1983.tb02251.x"
        },
        {
            "no": "20",
            "title": "On the Determinants of Net Foreign Investment",
            "date": "May 1983",
            "author": [
                "REN\u00c9 M. STULZ"
            ],
            "abstract": "",
            "link": "https://doi.org/10.1111/j.1540-6261.1983.tb02252.x"
        },
        {
            "no": "21",
            "title": "DISCUSSION",
            "date": "May 1983",
            "author": [
                "BERNARD DUMAS"
            ],
            "abstract": "",
            "link": "https://doi.org/10.1111/j.1540-6261.1983.tb02253.x"
        },
        {
            "no": "22",
            "title": "DISCUSSION",
            "date": "May 1983",
            "author": [
                "ALLAN W. KLEIDON",
                "PAUL PFLEIDERER"
            ],
            "abstract": "",
            "link": "https://doi.org/10.1111/j.1540-6261.1983.tb02254.x"
        },
        {
            "no": "23",
            "title": "DISCUSSION",
            "date": "May 1983",
            "author": [
                "JORGE BRAGA DE MACEDO"
            ],
            "abstract": "",
            "link": "https://doi.org/10.1111/j.1540-6261.1983.tb02255.x"
        },
        {
            "no": "24",
            "title": "Bankruptcy Costs and the New Bankruptcy Code",
            "date": "May 1983",
            "author": [
                "JEROLD B. WARNER",
                "MICHELLE J. WHITE"
            ],
            "abstract": "",
            "link": "https://doi.org/10.1111/j.1540-6261.1983.tb02256.x"
        },
        {
            "no": "25",
            "title": "The Behavior of the Common Stock of Bankrupt Firms",
            "date": "May 1983",
            "author": [
                "TRUMAN A. CLARK",
                "MARK I. WEINSTEIN"
            ],
            "abstract": "",
            "link": "https://doi.org/10.1111/j.1540-6261.1983.tb02257.x"
        },
        {
            "no": "26",
            "title": "The Resolution of Claims in Financial Distress the Case of Massey Ferguson",
            "date": "May 1983",
            "author": [
                "CARLISS Y. BALDWIN",
                "SCOTT P. MASON"
            ],
            "abstract": "",
            "link": "https://doi.org/10.1111/j.1540-6261.1983.tb02258.x"
        },
        {
            "no": "27",
            "title": "DISCUSSION",
            "date": "May 1983",
            "author": [
                "EDWARD I. ALTMAN"
            ],
            "abstract": "",
            "link": "https://doi.org/10.1111/j.1540-6261.1983.tb02259.x"
        },
        {
            "no": "28",
            "title": "DISCUSSION",
            "date": "May 1983",
            "author": [
                "W. M. TAYLOR"
            ],
            "abstract": "",
            "link": "https://doi.org/10.1111/j.1540-6261.1983.tb02260.x"
        },
        {
            "no": "29",
            "title": "The Arbitrage Pricing Model and Returns on Assets Under Uncertain Inflation*",
            "date": "May 1983",
            "author": [
                "JAMES BICKSLER",
                "EDWIN ELTON",
                "MARTIN GRUBER",
                "JOEL RENTZLER"
            ],
            "abstract": "",
            "link": "https://doi.org/10.1111/j.1540-6261.1983.tb02261.x"
        },
        {
            "no": "30",
            "title": "Tests of the Fisher Hypothesis with International Data: Theory and Evidence",
            "date": "May 1983",
            "author": [
                "ALEX KANE",
                "LEONARD ROSENTHAL",
                "GRETA LJUNG"
            ],
            "abstract": "",
            "link": "https://doi.org/10.1111/j.1540-6261.1983.tb02262.x"
        },
        {
            "no": "31",
            "title": "The Impact of Real Factors and Inflation on the Performance of the U.S. Stock Market From 1960 to 1980",
            "date": "May 1983",
            "author": [
                "MYRON J. GORDON"
            ],
            "abstract": "",
            "link": "https://doi.org/10.1111/j.1540-6261.1983.tb02263.x"
        },
        {
            "no": "32",
            "title": "DISCUSSION",
            "date": "May 1983",
            "author": [
                "ZVI BODIE"
            ],
            "abstract": "",
            "link": "https://doi.org/10.1111/j.1540-6261.1983.tb02264.x"
        },
        {
            "no": "33",
            "title": "DISCUSSION",
            "date": "May 1983",
            "author": [
                "DAVID M. MODEST"
            ],
            "abstract": "",
            "link": "https://doi.org/10.1111/j.1540-6261.1983.tb02265.x"
        },
        {
            "no": "34",
            "title": "DISCUSSION",
            "date": "May 1983",
            "author": [
                "SUSAN M. WACHTER"
            ],
            "abstract": "",
            "link": "https://doi.org/10.1111/j.1540-6261.1983.tb02266.x"
        },
        {
            "no": "35",
            "title": "The Interaction of Financing and Investment Decisions When the Firm has Unused Tax Credits\u2020\u2020",
            "date": "May 1983",
            "author": [
                "WILBUR G. LEWELLEN",
                "IAN COOPER",
                "JULIAN R. FRANKS"
            ],
            "abstract": "",
            "link": "https://doi.org/10.1111/j.1540-6261.1983.tb02267.x"
        },
        {
            "no": "36",
            "title": "A General Equilibrium Simulation Study of Subsidies to Municipal Expenditures",
            "date": "May 1983",
            "author": [
                "ROGER H. GORDON",
                "JOEL SLEMROD"
            ],
            "abstract": "",
            "link": "https://doi.org/10.1111/j.1540-6261.1983.tb02268.x"
        },
        {
            "no": "37",
            "title": "Valuation of Safe Harbor Tax Benefit Transfer Leases",
            "date": "May 1983",
            "author": [
                "FRANK J. FABOZZI",
                "UZI YAARI"
            ],
            "abstract": "",
            "link": "https://doi.org/10.1111/j.1540-6261.1983.tb02269.x"
        },
        {
            "no": "38",
            "title": "DISCUSSION",
            "date": "May 1983",
            "author": [
                "ALAN J. AUERBACH"
            ],
            "abstract": "",
            "link": "https://doi.org/10.1111/j.1540-6261.1983.tb02270.x"
        },
        {
            "no": "39",
            "title": "DISCUSSION",
            "date": "May 1983",
            "author": [
                "EARL R. ROLPH"
            ],
            "abstract": "",
            "link": "https://doi.org/10.1111/j.1540-6261.1983.tb02271.x"
        },
        {
            "no": "40",
            "title": "DISCUSSION",
            "date": "May 1983",
            "author": [
                "HAROLD BIERMAN JR."
            ],
            "abstract": "",
            "link": "https://doi.org/10.1111/j.1540-6261.1983.tb02272.x"
        },
        {
            "no": "41",
            "title": "AN EMPIRICAL ANALYSIS OF THE PRICING OF MORTGAGE\u2010BACKED SECURITIES",
            "date": "May 1983",
            "author": [
                "LEE WAKEMAN",
                "KENNETH B. DUNN",
                "KENNETH J. SINGLETON"
            ],
            "abstract": "",
            "link": "https://doi.org/10.1111/j.1540-6261.1983.tb02273.x"
        },
        {
            "no": "42",
            "title": "Relative Risk in Municipal and Corporate Debt",
            "date": "May 1983",
            "author": [
                "JEFFREY L. SKELTON"
            ],
            "abstract": "",
            "link": "https://doi.org/10.1111/j.1540-6261.1983.tb02274.x"
        },
        {
            "no": "43",
            "title": "Stochastic Processes for Interest Rates and Equilibrium Bond Prices",
            "date": "May 1983",
            "author": [
                "TERRY A. MARSH",
                "ERIC R. ROSENFELD"
            ],
            "abstract": "",
            "link": "https://doi.org/10.1111/j.1540-6261.1983.tb02275.x"
        },
        {
            "no": "44",
            "title": "DISCUSSION",
            "date": "May 1983",
            "author": [
                "S. M. TURNBULL"
            ],
            "abstract": "",
            "link": "https://doi.org/10.1111/j.1540-6261.1983.tb02276.x"
        },
        {
            "no": "45",
            "title": "DISCUSSION",
            "date": "May 1983",
            "author": [
                "CLIFFORD W. SMITH Jr."
            ],
            "abstract": "",
            "link": "https://doi.org/10.1111/j.1540-6261.1983.tb02277.x"
        },
        {
            "no": "46",
            "title": "DISCUSSION",
            "date": "May 1983",
            "author": [
                "MICHAEL R. GIBBONS"
            ],
            "abstract": "",
            "link": "https://doi.org/10.1111/j.1540-6261.1983.tb02278.x"
        },
        {
            "no": "47",
            "title": "AMERICAN FINANCE ASSOCIATION: Minutes of the Annual Membership Meeting",
            "date": "May 1983",
            "author": [],
            "abstract": "",
            "link": "https://doi.org/10.1111/j.1540-6261.1983.tb02279.x"
        },
        {
            "no": "48",
            "title": "AMERICAN FINANCE ASSOCIATION: Report of the Executive Secretary and Treasurer for the Year Ending September 30, 1982",
            "date": "May 1983",
            "author": [],
            "abstract": "",
            "link": "https://doi.org/10.1111/j.1540-6261.1983.tb02280.x"
        },
        {
            "no": "49",
            "title": "Report of the Managing Editor of the Journal of Finance for 1982",
            "date": "May 1983",
            "author": [],
            "abstract": "",
            "link": "https://doi.org/10.1111/j.1540-6261.1983.tb02281.x"
        },
        {
            "no": "50",
            "title": "Back Matter",
            "date": "May 1983",
            "author": [],
            "abstract": "",
            "link": "https://doi.org/10.1111/j.1540-6261.1983.tb00916.x"
        }
    ]
}