{
    "journal": "JF",
    "volume": "11",
    "issue": "3",
    "date": "September 1956",
    "page": "Pages: i-x, 313-411, xi-xviii",
    "article": [
        {
            "no": "1",
            "title": "Front Matter",
            "date": "September 1956",
            "author": [],
            "abstract": "",
            "link": "https://doi.org/10.1111/j.1540-6261.1956.tb00086.x"
        },
        {
            "no": "2",
            "title": "SOME FACTORS AFFECTING THE INCREASED RELATIVE USE OF CURRENCY SINCE 1939*",
            "date": "September 1956",
            "author": [
                "Stephen L. McDonald"
            ],
            "abstract": "",
            "link": "https://doi.org/10.1111/j.1540-6261.1956.tb00107.x"
        },
        {
            "no": "3",
            "title": "A GRAPHIC ANALYSIS OF THE THEORY OF THE DETERMINATION OF THE MONEY SUPPLY",
            "date": "September 1956",
            "author": [
                "Arnold P. Collery"
            ],
            "abstract": "",
            "link": "https://doi.org/10.1111/j.1540-6261.1956.tb00108.x"
        },
        {
            "no": "4",
            "title": "THE CREDIT EXPANSION EQUATIONS OF AN INDIVIDUAL BANK*",
            "date": "September 1956",
            "author": [
                "Robert E. Emmer"
            ],
            "abstract": "",
            "link": "https://doi.org/10.1111/j.1540-6261.1956.tb00109.x"
        },
        {
            "no": "5",
            "title": "THE LARGE CREDIT UNION",
            "date": "September 1956",
            "author": [
                "John T. Croteau"
            ],
            "abstract": "",
            "link": "https://doi.org/10.1111/j.1540-6261.1956.tb00110.x"
        },
        {
            "no": "6",
            "title": "THE THEORETICAL VALUE OF A STOCK RIGHT: A COMMENT",
            "date": "September 1956",
            "author": [
                "Stephen H. Archer"
            ],
            "abstract": "",
            "link": "https://doi.org/10.1111/j.1540-6261.1956.tb00111.x"
        },
        {
            "no": "7",
            "title": "THE THEORETICAL VALUE OF A STOCK RIGHT: A COMMENT",
            "date": "September 1956",
            "author": [
                "William Beranek"
            ],
            "abstract": "",
            "link": "https://doi.org/10.1111/j.1540-6261.1956.tb00112.x"
        },
        {
            "no": "8",
            "title": "THE DEVELOPMENT OF A GENERAL QUASI\u2010REORGANIZATION CONCEPT*",
            "date": "September 1956",
            "author": [
                "James S. Schindler"
            ],
            "abstract": "",
            "link": "https://doi.org/10.1111/j.1540-6261.1956.tb00113.x"
        },
        {
            "no": "9",
            "title": "THE VALUATION OF CLOSELY HELD INDUSTRIAL SHARES FOR FEDERAL TAX PURPOSES*",
            "date": "September 1956",
            "author": [
                "Adolph Edward Grunewald"
            ],
            "abstract": "",
            "link": "https://doi.org/10.1111/j.1540-6261.1956.tb00114.x"
        },
        {
            "no": "10",
            "title": "STUDIES IN THE DISTRIBUTION OF TAX BURDENS BY INCOME GROUPS: A CRITIQUE*",
            "date": "September 1956",
            "author": [
                "Eli Schwartz"
            ],
            "abstract": "",
            "link": "https://doi.org/10.1111/j.1540-6261.1956.tb00115.x"
        },
        {
            "no": "11",
            "title": "THE CENTRALIZATION OF GOVERNMENTAL EXPENDITURES FOR EDUCATION AND HIGHWAYS IN NORTH CAROLINA, 1929\u201352",
            "date": "September 1956",
            "author": [
                "Charles E. Ratliff Jr."
            ],
            "abstract": "",
            "link": "https://doi.org/10.1111/j.1540-6261.1956.tb00116.x"
        },
        {
            "no": "12",
            "title": "ACTIVITIES OF STUDENT AFFILIATES",
            "date": "September 1956",
            "author": [],
            "abstract": "",
            "link": "https://doi.org/10.1111/j.1540-6261.1956.tb00117.x"
        },
        {
            "no": "13",
            "title": "BOOK REVIEWS",
            "date": "September 1956",
            "author": [],
            "abstract": "Book reviewed in this article:\nCorporate Reorganizations: Their Federal Tax Status. By Robert S. Holzman. 2d ed.\nRaising Capital with Convertible Securities. By C. James Pilcher.\nUsing Instalment Credit. By Clyde William Phelps\nQuestions and Answers on Insurance. By William E. Boyd, Jr., and Cameron S. Toole\nA History of the Massachusetts Hospital Life Insurance Company. By Gerald T. White.\nForeign Investment and Taxation. By E. R. Barlow and Ira T. Wender\nCapital Formation and Foreign Investment in Underdeveloped Areas. By Charles Wolf, Jr., and Sidney C. Sufrin.\nIntroduction to Investments. By John C. Clendenin. 2d ed.\nA Study of Saving in the United States. By Raymond W. Goldsmith\nInvestor's Handbook. By Jacob O. Kamm.\nCapital Formation and Economic Growth. By Universities\u2010National Bureau Committee for Economic Research.\nFlow of Funds in the United States, 1939\u20131953. By Board of Governors of the Federal Reserve System\nThe Money Market and Its Institutions. By Marcus Nadler, Sipa Heller, and Samuel S. Shipman.\nPolicies To Combat Depression. By Universities\u2010National Bureau Committee for Economic Research.\nFiscal Policy: Its Techniques and Institutional Setting. By James A. Maxwell\nHousing Taxation. By Walter A. Morton.\nThe Pennsylvania Tax Problem, 1955. By Tax Institute Conference.",
            "link": "https://doi.org/10.1111/j.1540-6261.1956.tb00118.x"
        },
        {
            "no": "14",
            "title": "BOOKS RECEIVED",
            "date": "September 1956",
            "author": [
                "Clyde William Phelps"
            ],
            "abstract": "",
            "link": "https://doi.org/10.1111/j.1540-6261.1956.tb00119.x"
        },
        {
            "no": "15",
            "title": "Back Matter",
            "date": "September 1956",
            "author": [],
            "abstract": "",
            "link": "https://doi.org/10.1111/j.1540-6261.1956.tb00087.x"
        }
    ]
}